Spectralanalysis/__init__.py
Spectralanalysis/data_augmentation_module.py
Spectralanalysis/data_module.py
Spectralanalysis/machine_learning.py
Spectralanalysis/processing_module.py
Spectralanalysis/spectral_analysis_module.py
Spectralanalysis/visualization_module.py
tests/__init__.py
tests/data_augment_tests.py
tests/data_module_tests.py
tests/machine_learning_tests.py
tests/processing_module_tests.py
tests/spectral_analysis_tests.py
tests/test_integration.py
tests/visualization_tests.py
Spectralanalysis-0.1.6.dist-info/METADATA
Spectralanalysis-0.1.6.dist-info/WHEEL
Spectralanalysis-0.1.6.dist-info/top_level.txt
Spectralanalysis-0.1.6.dist-info/RECORD
